firefed/__init__.py
firefed/__main__.py
firefed/__version__.py
firefed/output.py
firefed/session.py
firefed/util.py
firefed/feature/__init__.py
firefed/feature/addons.py
firefed/feature/bookmarks.py
firefed/feature/cookies.py
firefed/feature/feature.py
firefed/feature/forms.py
firefed/feature/history.py
firefed/feature/infect.py
firefed/feature/logins.py
firefed/feature/permissions.py
firefed/feature/places.py
firefed/feature/preferences.py
firefed/feature/summary.py
firefed/feature/visits.py
firefed-0.1.14.dist-info/METADATA
firefed-0.1.14.dist-info/RECORD
firefed-0.1.14.dist-info/WHEEL
firefed-0.1.14.dist-info/entry_points.txt
firefed-0.1.14.dist-info/top_level.txt
