Metadata-Version: 2.1
Name: firefed
Version: 0.1.14
Summary: A tool for Firefox profile analysis, data extraction, forensics and hardening
Home-page: https://github.com/numirias/firefed
Author: numirias
Author-email: numirias@users.noreply.github.com
License: MIT
Keywords: firefox security privacy forensics
Platform: UNKNOWN
Classifier: Development Status :: 3 - Alpha
Classifier: License :: OSI Approved :: MIT License
Classifier: Operating System :: Unix
Classifier: Operating System :: POSIX :: Linux
Classifier: Programming Language :: Python
Classifier: Programming Language :: Python :: 3
Classifier: Programming Language :: Python :: 3.6
Classifier: Programming Language :: Python :: 3.7
Classifier: Topic :: Security
Classifier: Topic :: Internet :: WWW/HTTP :: Browsers
Requires-Python: >=3
Requires-Dist: colorama
Requires-Dist: lz4
Requires-Dist: requests
Requires-Dist: attrs (>=17.4)
